binance_data/__init__.py
binance_data/client.py
binance_data-0.1.4.dist-info/METADATA
binance_data-0.1.4.dist-info/WHEEL
binance_data-0.1.4.dist-info/top_level.txt
binance_data-0.1.4.dist-info/RECORD
